libinjection.cpython-310-darwin.so
libinjection_python-1.1.6.dist-info/LICENSE
libinjection_python-1.1.6.dist-info/METADATA
libinjection_python-1.1.6.dist-info/WHEEL
libinjection_python-1.1.6.dist-info/top_level.txt
libinjection_python-1.1.6.dist-info/RECORD
