Metadata-Version: 2.1
Name: libinjection-python
Version: 1.1.6
Summary: Libinjection Python Wrapper
Home-page: https://github.com/wzhvictor/libinjection-python
Author: wzhvictor
Author-email: wzhvictor@outlook.com
Classifier: Development Status :: 4 - Beta
Classifier: Environment :: Console
Classifier: Intended Audience :: Developers
Classifier: License :: OSI Approved :: GNU General Public License v3 or later (GPLv3+)
Classifier: Natural Language :: English
Classifier: Operating System :: Unix
Classifier: Programming Language :: Cython
Classifier: Topic :: Software Development :: Libraries :: Python Modules
License-File: LICENSE
